<annotation>
	<folder>Crosswalk</folder>
	<filename>Cross (907).png</filename>
	<path>C:\Users\janku\Documents\AI\Projects\GoogleReCaptcha\archive\Google_Recaptcha_V2_Images_Dataset\images\Crosswalk\Cross (907).png</path>
	<source>
		<database>Unknown</database>
	</source>
	<size>
		<width>120</width>
		<height>120</height>
		<depth>3</depth>
	</size>
	<segmented>0</segmented>
	<object>
		<name>Crosswalk</name>
		<pose>Unspecified</pose>
		<truncated>1</truncated>
		<difficult>0</difficult>
		<bndbox>
			<xmin>5</xmin>
			<ymin>105</ymin>
			<xmax>120</xmax>
			<ymax>120</ymax>
		</bndbox>
	</object>
	<object>
		<name>Crosswalk</name>
		<pose>Unspecified</pose>
		<truncated>1</truncated>
		<difficult>0</difficult>
		<bndbox>
			<xmin>51</xmin>
			<ymin>92</ymin>
			<xmax>120</xmax>
			<ymax>110</ymax>
		</bndbox>
	</object>
	<object>
		<name>Crosswalk</name>
		<pose>Unspecified</pose>
		<truncated>1</truncated>
		<difficult>0</difficult>
		<bndbox>
			<xmin>89</xmin>
			<ymin>76</ymin>
			<xmax>120</xmax>
			<ymax>94</ymax>
		</bndbox>
	</object>
	<object>
		<name>Crosswalk</name>
		<pose>Unspecified</pose>
		<truncated>1</truncated>
		<difficult>0</difficult>
		<bndbox>
			<xmin>115</xmin>
			<ymin>69</ymin>
			<xmax>120</xmax>
			<ymax>77</ymax>
		</bndbox>
	</object>
	<object>
		<name>Crosswalk</name>
		<pose>Unspecified</pose>
		<truncated>0</truncated>
		<difficult>0</difficult>
		<bndbox>
			<xmin>53</xmin>
			<ymin>39</ymin>
			<xmax>74</xmax>
			<ymax>48</ymax>
		</bndbox>
	</object>
	<object>
		<name>Crosswalk</name>
		<pose>Unspecified</pose>
		<truncated>0</truncated>
		<difficult>0</difficult>
		<bndbox>
			<xmin>72</xmin>
			<ymin>46</ymin>
			<xmax>102</xmax>
			<ymax>49</ymax>
		</bndbox>
	</object>
	<object>
		<name>Crosswalk</name>
		<pose>Unspecified</pose>
		<truncated>1</truncated>
		<difficult>0</difficult>
		<bndbox>
			<xmin>102</xmin>
			<ymin>47</ymin>
			<xmax>120</xmax>
			<ymax>55</ymax>
		</bndbox>
	</object>
	<object>
		<name>Crosswalk</name>
		<pose>Unspecified</pose>
		<truncated>0</truncated>
		<difficult>0</difficult>
		<bndbox>
			<xmin>2</xmin>
			<ymin>38</ymin>
			<xmax>30</xmax>
			<ymax>42</ymax>
		</bndbox>
	</object>
</annotation>
