<annotation>
	<folder>Crosswalk</folder>
	<filename>Cross (740).png</filename>
	<path>C:\Users\janku\Documents\AI\Projects\GoogleReCaptcha\archive\Google_Recaptcha_V2_Images_Dataset\images\Crosswalk\Cross (740).png</path>
	<source>
		<database>Unknown</database>
	</source>
	<size>
		<width>120</width>
		<height>120</height>
		<depth>3</depth>
	</size>
	<segmented>0</segmented>
	<object>
		<name>Crosswalk</name>
		<pose>Unspecified</pose>
		<truncated>1</truncated>
		<difficult>0</difficult>
		<bndbox>
			<xmin>102</xmin>
			<ymin>17</ymin>
			<xmax>120</xmax>
			<ymax>35</ymax>
		</bndbox>
	</object>
	<object>
		<name>Crosswalk</name>
		<pose>Unspecified</pose>
		<truncated>0</truncated>
		<difficult>0</difficult>
		<bndbox>
			<xmin>77</xmin>
			<ymin>24</ymin>
			<xmax>109</xmax>
			<ymax>43</ymax>
		</bndbox>
	</object>
	<object>
		<name>Crosswalk</name>
		<pose>Unspecified</pose>
		<truncated>0</truncated>
		<difficult>0</difficult>
		<bndbox>
			<xmin>44</xmin>
			<ymin>35</ymin>
			<xmax>85</xmax>
			<ymax>52</ymax>
		</bndbox>
	</object>
	<object>
		<name>Crosswalk</name>
		<pose>Unspecified</pose>
		<truncated>1</truncated>
		<difficult>0</difficult>
		<bndbox>
			<xmin>81</xmin>
			<ymin>78</ymin>
			<xmax>120</xmax>
			<ymax>103</ymax>
		</bndbox>
	</object>
</annotation>
